MarginRequirement/__init__.py
MarginRequirement/main.py
MarginRequirement-0.2.dist-info/METADATA
MarginRequirement-0.2.dist-info/WHEEL
MarginRequirement-0.2.dist-info/top_level.txt
MarginRequirement-0.2.dist-info/RECORD
